germgenie/main.py
germgenie-0.1.10.dist-info/LICENSE
germgenie-0.1.10.dist-info/METADATA
germgenie-0.1.10.dist-info/WHEEL
germgenie-0.1.10.dist-info/entry_points.txt
germgenie-0.1.10.dist-info/top_level.txt
germgenie-0.1.10.dist-info/RECORD
