Metadata-Version: 2.1
Name: germgenie
Version: 0.1.10
Summary: Python wrapper for multi-sample 16S classification using EMU
Author-email: Sander Boden <s.boden1@avans.nl>, Daan Brackel <dcj.brackel@student.avans.nl>
Project-URL: Repository, https://github.com/Avans-ATLS/GermGenie
Project-URL: Issues, https://github.com/Avans-ATLS/GermGenie/issues
Classifier: Programming Language :: Python :: 3
Classifier: License :: OSI Approved :: MIT License
Classifier: Operating System :: Unix
Requires-Python: >=3.7
License-File: LICENSE
Requires-Dist: plotly >=5.18.0
Requires-Dist: osfclient ==0.0.5
Requires-Dist: pandas ==1.3.5
Requires-Dist: biopython ==1.78
